<?xml version="1.0" encoding="UTF-8"?>
<sv:node sv:name="aantal-honderdjarigen-in-veertien-jaar-verdubbeld" xmlns:sv="http://www.jcp.org/jcr/sv/1.0" xmlns:xsi="http://www.w3.org/2001/XMLSchema-instance">
  <sv:property sv:name="jcr:primaryType" sv:type="Name">
    <sv:value>mgnl:news</sv:value>
  </sv:property>
  <sv:property sv:name="jcr:uuid" sv:type="String">
    <sv:value>0cfd7eb3-2852-4521-bded-1b53577e9a10</sv:value>
  </sv:property>
  <sv:property sv:name="comments" sv:type="Boolean">
    <sv:value>false</sv:value>
  </sv:property>
  <sv:property sv:name="jcr:createdBy" sv:type="String">
    <sv:value>admin</sv:value>
  </sv:property>
  <sv:property sv:name="mgnl:created" sv:type="Date">
    <sv:value>2014-10-28T08:23:39.333+01:00</sv:value>
  </sv:property>
  <sv:property sv:name="mgnl:createdBy" sv:type="String">
    <sv:value>superuser</sv:value>
  </sv:property>
  <sv:property sv:name="mgnl:lastModified" sv:type="Date">
    <sv:value>2014-10-28T08:23:39.333+01:00</sv:value>
  </sv:property>
  <sv:property sv:name="mgnl:lastModifiedBy" sv:type="String">
    <sv:value>superuser</sv:value>
  </sv:property>
  <sv:property sv:name="startDate" sv:type="Date">
    <sv:value>2014-10-29T00:00:00.000+01:00</sv:value>
  </sv:property>
  <sv:property sv:name="summary" sv:type="String">
    <sv:value>Bijna 2.200 Nederlanders zijn honderd jaar of ouder. Dat is ruim twee keer zo veel als in 2000. Tussen nu en 2025 zal het aantal 100-plussers waarschijnlijk weer verdubbelen. </sv:value>
  </sv:property>
  <sv:property sv:name="text" sv:type="String">
    <sv:value>&lt;p&gt;Bijna 2.200 Nederlanders zijn honderd jaar of ouder. Dat is ruim twee keer zo veel als in 2000. Tussen nu en 2025 zal het aantal 100-plussers waarschijnlijk weer verdubbelen.&amp;nbsp;&lt;/p&gt;

&lt;p&gt;Dat meldt&amp;nbsp;het Centraal Bureau voor de Statistiek (&lt;a href="http://www.cbs.nl/nl-NL/menu/themas/bevolking/publicaties/artikelen/archief/2014/2014-4149-wm.htm" style="box-sizing: border-box; -webkit-tap-highlight-color: transparent; margin: 0px; padding: 0px; border: 0px; font-family: inherit; font-style: inherit; font-variant: inherit; font-weight: inherit; font-stretch: inherit; line-height: inherit; vertical-align: baseline; color: rgb(1, 0, 80);" target="_blank"&gt;CBS&lt;/a&gt;) maandag.&lt;/p&gt;

&lt;p&gt;Dat er zo veel hoogbejaarden zijn, komt volgens het CBS door &amp;#39;&amp;#39;dalende sterftecijfers op gevorderde leeftijd&amp;#39;&amp;#39;. De 100-plussers zijn &amp;#39;&amp;#39;opvallend gezond&amp;#39;&amp;#39; en hebben weinig last van ouderdomsziektes.&lt;/p&gt;

&lt;p&gt;Onder de 100-plussers zijn nu veel meer vrouwen dan mannen, maar in de komende jaren zullen ook meer mannen hun honderdste verjaardag halen.&lt;/p&gt;

&lt;p&gt;&amp;#39;&amp;#39;Een verklaring hiervoor is dat mannen steeds minder zijn gaan roken en vrouwen juist meer&amp;#39;&amp;#39;, aldus het CBS.&lt;/p&gt;

&lt;p&gt;Nederland heeft in verhouding tot de rest van&amp;nbsp;Europa weinig 100-plussers. In Spanje, Frankrijk, Itali&amp;euml; en Griekenland is dit aantal meer dan twee keer zo hoog vanwege de hoge vergrijzing in die landen. Itali&amp;euml; en Griekenland behoren tot de meest vergrijsde landen van Europa.&lt;/p&gt;
</sv:value>
  </sv:property>
  <sv:property sv:name="title" sv:type="String">
    <sv:value>Aantal honderdjarigen in veertien jaar verdubbeld </sv:value>
  </sv:property>
</sv:node>
